{
  "1": "Edge-to-Cloud MLOps",
  "2": "Agenda",
  "3": "비즈니스 도전과제",
  "4": "SECTION 01 · 레퍼런스 아키텍처",
  "5": "Hybrid Reference Architecture",
  "6": "네트워크 · ExpressRoute",
  "7": "ExpressRoute Peering 비교",
  "8": "Global Reach & Virtual WAN",
  "9": "데이터 수집 · 실시간 vs 배치",
  "10": "데이터 마이그레이션 서비스",
  "11": "스토리지 매핑",
  "12": "데이터 분석 · 시뮬레이션",
  "13": "End-to-End MLOps 운영 스택",
  "14": "SECTION 02 · Azure ML & MLOps",
  "15": "Azure Machine Learning",
  "16": "MLOps 레퍼런스 아키텍처",
  "17": "MLOps · Azure 서비스 매핑",
  "18": "SECTION 03 · 제조 Closed-loop",
  "19": "Closed-loop MLOps Pipeline",
  "20": "제조 Edge-to-Cloud 아키텍처",
  "21": "IoT Edge ML 추론",
  "22": "SECTION 04 · 고객 사례",
  "23": "P&G · 사례 개요",
  "24": "P&G IoT Operations + Arc",
  "25": "3M · 사례 개요",
  "26": "3M IoT Edge + SQL Edge",
  "27": "Siemens Industrial Edge",
  "28": "Closed-loop 적용 사례",
  "29": "SECTION 05 · MLOps CI/CD",
  "30": "MLOps CI/CD 자동화",
  "31": "GitHub Actions 워크플로",
  "32": "보안 · 거버넌스 · 로드맵",
  "33": "Key Takeaways"
}
